{
  "task": "M5.12",
  "script": "m5_12_b12_hard.py",
  "nr": 32,
  "state0": "m5_12_b15_seed_rgauss_k2_n32.npz",
  "rungs": [
    {
      "rung": 1.0,
      "a2_star": 0.3037246487881664,
      "hist": [
        {
          "iter": 1,
          "F_norm": 3224.4472194328823,
          "F_rel": 0.2545002357198523,
          "omega_bal": 7.453351724333504,
          "S0": 45.03475123897234,
          "Q2": -0.8106708106863607,
          "lam": 1.0,
          "accepted": true,
          "lsmr_stop": 7,
          "damp_frac": 0.0,
          "wall_s": 1524.8
        },
        {
          "iter": 2,
          "F_norm": 187.75323529853594,
          "F_rel": 0.014819049402534937,
          "omega_bal": 7.375088102555581,
          "S0": 44.088965901442705,
          "Q2": -0.8105792595160111,
          "lam": 1.0,
          "accepted": true,
          "lsmr_stop": 2,
          "damp_frac": 0.001,
          "wall_s": 3375.0
        },
        {
          "iter": 3,
          "F_norm": 187.41501581893647,
          "F_rel": 0.014792354303677573,
          "omega_bal": 7.3752761259363995,
          "S0": 44.08877201631573,
          "Q2": -0.8105343662348687,
          "lam": 1.0,
          "accepted": true,
          "lsmr_stop": 2,
          "damp_frac": 0.0003333333333333333,
          "wall_s": 3822.0
        },
        {
          "iter": 4,
          "F_norm": 187.40992506760472,
          "F_rel": 0.01479195249917412,
          "omega_bal": 7.375405574068622,
          "S0": 44.088632991617054,
          "Q2": -0.810503358821677,
          "lam": 1.0,
          "accepted": true,
          "lsmr_stop": 2,
          "damp_frac": 0.0003333333333333333,
          "wall_s": 4693.3
        },
        {
          "iter": 5,
          "F_norm": 187.40943585588403,
          "F_rel": 0.014791913886509758,
          "omega_bal": 7.375536327533774,
          "S0": 44.08849194564417,
          "Q2": -0.8104720290521072,
          "lam": 1.0,
          "accepted": true,
          "lsmr_stop": 2,
          "damp_frac": 0.0003333333333333333,
          "wall_s": 5548.5
        }
      ],
      "omega_bal_end": 7.375536327533774,
      "S0_end": 44.08849194564417,
      "Q2_end": -0.8104720290521072,
      "Q2_mix": -0.8100970169102197,
      "Q2_pos": 0.00034802764950114806,
      "Q2_cross": -0.0007230397913886577,
      "Shat_end": 88.1769838912883,
      "BG5": {
        "H_mean": 3.552713678800501e-15,
        "H_min": -43.98259182583012,
        "H_max": 43.98749979406051,
        "drift_rel": 2.476137948994299e+16
      },
      "H_swing": 87.97009161989064,
      "H_swing_over_S0": 1.9953073407080293,
      "verdict": "stalled_or_partial"
    }
  ]
}