{
  "task": "M5.12",
  "script": "m5_12_b12_hard.py",
  "nr": 32,
  "state0": "m5_12_b14_seed_wide_rz_n32.npz",
  "rungs": [
    {
      "rung": 1.0,
      "a2_star": 0.3037246478130574,
      "hist": [
        {
          "iter": 1,
          "F_norm": 2229.8383038128773,
          "F_rel": 0.18038100987641648,
          "omega_bal": 7.513791399053571,
          "S0": 44.99008422593481,
          "Q2": -0.7968902964277191,
          "lam": 1.0,
          "accepted": true,
          "lsmr_stop": 7,
          "damp_frac": 0.0,
          "wall_s": 1531.7
        },
        {
          "iter": 2,
          "F_norm": 194.34853584212541,
          "F_rel": 0.015721671433870654,
          "omega_bal": 7.453981835192244,
          "S0": 44.2671951580534,
          "Q2": -0.7967193133922521,
          "lam": 1.0,
          "accepted": true,
          "lsmr_stop": 2,
          "damp_frac": 0.001,
          "wall_s": 3375.9
        },
        {
          "iter": 3,
          "F_norm": 193.90892011589747,
          "F_rel": 0.015686109066626826,
          "omega_bal": 7.454231795952901,
          "S0": 44.26696210560816,
          "Q2": -0.7966616877490793,
          "lam": 1.0,
          "accepted": true,
          "lsmr_stop": 2,
          "damp_frac": 0.0003333333333333333,
          "wall_s": 3819.8
        },
        {
          "iter": 4,
          "F_norm": 193.89798631873097,
          "F_rel": 0.015685224585733612,
          "omega_bal": 7.454399229111066,
          "S0": 44.266795353273054,
          "Q2": -0.7966228996704814,
          "lam": 1.0,
          "accepted": true,
          "lsmr_stop": 2,
          "damp_frac": 0.0003333333333333333,
          "wall_s": 4689.4
        },
        {
          "iter": 5,
          "F_norm": 193.8937064504827,
          "F_rel": 0.01568487836916919,
          "omega_bal": 7.454566660733108,
          "S0": 44.266626375393045,
          "Q2": -0.7965840745521575,
          "lam": 1.0,
          "accepted": true,
          "lsmr_stop": 2,
          "damp_frac": 0.0003333333333333333,
          "wall_s": 5560.0
        }
      ],
      "omega_bal_end": 7.454566660733108,
      "S0_end": 44.266626375393045,
      "Q2_end": -0.7965840745521575,
      "Q2_mix": -0.7941387279782504,
      "Q2_pos": 0.00205224211893551,
      "Q2_cross": -0.004497588692842669,
      "Shat_end": 88.5332527507859,
      "BG5": {
        "H_mean": -1.8253487610309092e-11,
        "H_min": -43.970237115287674,
        "H_max": 44.14590273078827,
        "drift_rel": 4827359117734.315
      },
      "H_swing": 88.11613984607595,
      "H_swing_over_S0": 1.9905772601423721,
      "verdict": "stalled_or_partial"
    }
  ]
}