{
 "task": "M5.21.1",
 "phase": "P0",
 "delta": 0.3,
 "G_T": 8.0,
 "wscale": 0.0007240238793069094,
 "grid": [
  128,
  256,
  1.0
 ],
 "c4_sp": [
  9.3,
  65.09,
  513.027,
  4097.0081
 ],
 "c4_sm": [
  -6.7,
  65.09,
  -510.973,
  4097.0081
 ],
 "SP1": {
  "ok": true,
  "max_abs": 0.0
 },
 "SP2": {
  "ok": true,
  "sp": {
   "rows": [
    {
     "branch": "g_timelike",
     "label": [
      8.0
     ],
     "label_drift_under_orbit": 8.881784197001252e-15,
     "V4_on_orbit_max": 5.35746995171798e-23
    },
    {
     "branch": "one_timelike",
     "label": [
      1.0
     ],
     "label_drift_under_orbit": 2.4424906541753444e-15,
     "V4_on_orbit_max": 3.3606263423320324e-24
    },
    {
     "branch": "delta_timelike",
     "label": [
      0.3
     ],
     "label_drift_under_orbit": 7.216449660063518e-16,
     "V4_on_orbit_max": 1.344250536932813e-23
    },
    {
     "branch": "zero_timelike",
     "label": [
      0.0
     ],
     "label_drift_under_orbit": 2.408289223512419e-15,
     "V4_on_orbit_max": 3.321650302726873e-24
    }
   ],
   "n_branches_distinct": 4,
   "disjoint": true
  },
  "sm": {
   "rows": [
    {
     "branch": "g_timelike",
     "label": [
      -8.0
     ],
     "label_drift_under_orbit": 7.105427357601002e-15,
     "V4_on_orbit_max": 7.525607606924522e-24
    },
    {
     "branch": "one_timelike",
     "label": [
      1.0
     ],
     "label_drift_under_orbit": 7.216449660063518e-15,
     "V4_on_orbit_max": 6.755496899901437e-23
    },
    {
     "branch": "delta_timelike",
     "label": [
      0.3
     ],
     "label_drift_under_orbit": 4.6629367034256575e-15,
     "V4_on_orbit_max": 1.0126520665622554e-22
    },
    {
     "branch": "zero_timelike",
     "label": [
      0.0
     ],
     "label_drift_under_orbit": 2.890647100284284e-15,
     "V4_on_orbit_max": 2.0942055322831392e-23
    }
   ],
   "n_branches_distinct": 4,
   "disjoint": true
  }
 },
 "SP3": {
  "ok": true,
  "rel_worst": 1.744207199115686e-11,
  "rows": [
   {
    "delta": 0.0,
    "sp": {
     "eigs": [
      0.0,
      0.0,
      0.0,
      0.0,
      0.0,
      0.0,
      2.0190728014337006e-19,
      0.0026046558412492204,
      0.01722581667566072,
      6127.331994048237
     ],
     "omegas": [
      0.0,
      0.0,
      0.0,
      0.0,
      0.0,
      0.0,
      4.49340939758854e-10,
      0.051035828995414784,
      0.1312471587336683,
      78.27727635813753
     ],
     "n_zero": 7,
     "n_negative": 0,
     "FD_crosscheck_rel": 1.744207199115686e-11
    },
    "sm": {
     "eigs": [
      -4.153953003289829e-21,
      0.0,
      0.0,
      0.0,
      0.0,
      0.0,
      0.0,
      0.0026931297830110534,
      0.023632877722982514,
      6127.325498513247
     ],
     "omegas": [
      0.0,
      0.0,
      0.0,
      0.0,
      0.0,
      0.0,
      0.0,
      0.051895373425875385,
      0.15372988558826978,
      78.27723486757338
     ],
     "n_zero": 7,
     "n_negative": 0,
     "FD_crosscheck_rel": 1.744207199115686e-11
    },
    "ladder_rel_diff_sm_vs_sp": 0.17130067478431502
   },
   {
    "delta": 0.1,
    "sp": {
     "eigs": [
      0.0,
      0.0,
      0.0,
      0.0,
      0.0,
      0.0,
      1.5160139574983116e-05,
      0.0024855506665189663,
      0.01738889758112984,
      6127.331994160689
     ],
     "omegas": [
      0.0,
      0.0,
      0.0,
      0.0,
      0.0,
      0.0,
      0.003893602390458368,
      0.049855297276407515,
      0.13186696925739153,
      78.27727635885583
     ],
     "n_zero": 6,
     "n_negative": 0,
     "FD_crosscheck_rel": 1.744207199115686e-11
    },
    "sm": {
     "eigs": [
      0.0,
      0.0,
      0.0,
      0.0,
      0.0,
      0.0,
      1.8354708618911912e-05,
      0.002611522697003267,
      0.023755371412533456,
      6127.3254985202575
     ],
     "omegas": [
      0.0,
      0.0,
      0.0,
      0.0,
      0.0,
      0.0,
      0.004284239561335466,
      0.05110305956597185,
      0.15412777625247648,
      78.27723486761816
     ],
     "n_zero": 6,
     "n_negative": 0,
     "FD_crosscheck_rel": 1.744207199115686e-11
    },
    "ladder_rel_diff_sm_vs_sp": 0.16881260804314094
   },
   {
    "delta": 0.3,
    "sp": {
     "eigs": [
      0.0,
      0.0,
      0.0,
      0.0,
      0.0,
      0.0,
      8.584444562205136e-05,
      0.0021703053139698414,
      0.01819054336630782,
      6127.332021577531
     ],
     "omegas": [
      0.0,
      0.0,
      0.0,
      0.0,
      0.0,
      0.0,
      0.009265227769572174,
      0.04658653575841244,
      0.1348723224620523,
      78.27727653398227
     ],
     "n_zero": 6,
     "n_negative": 0,
     "FD_crosscheck_rel": 1.744207199115686e-11
    },
    "sm": {
     "eigs": [
      0.0,
      0.0,
      0.0,
      0.0,
      0.0,
      0.0,
      0.00011209643942355274,
      0.0023727061876466287,
      0.02447411858441604,
      6127.325509349447
     ],
     "omegas": [
      0.0,
      0.0,
      0.0,
      0.0,
      0.0,
      0.0,
      0.010587560598341468,
      0.04871043202073483,
      0.15644206142983427,
      78.2772349367902
     ],
     "n_zero": 6,
     "n_negative": 0,
     "FD_crosscheck_rel": 1.744207199115686e-11
    },
    "ladder_rel_diff_sm_vs_sp": 0.15992709678333622
   },
   {
    "delta": 0.5,
    "sp": {
     "eigs": [
      0.0,
      0.0,
      0.0,
      0.0,
      0.0,
      0.0,
      0.00012816699273881035,
      0.001771015682904183,
      0.02007532463686389,
      6127.3324746000035
     ],
     "omegas": [
      0.0,
      0.0,
      0.0,
      0.0,
      0.0,
      0.0,
      0.011321086199601624,
      0.04208343715648929,
      0.1416874187670306,
      78.27727942768581
     ],
     "n_zero": 6,
     "n_negative": 0,
     "FD_crosscheck_rel": 1.744207199115686e-11
    },
    "sm": {
     "eigs": [
      0.0,
      0.0,
      0.0,
      0.0,
      0.0,
      0.0,
      0.00018448660033490327,
      0.001977999363712109,
      0.026513981039435936,
      6127.3257726403135
     ],
     "omegas": [
      0.0,
      0.0,
      0.0,
      0.0,
      0.0,
      0.0,
      0.013582584449761513,
      0.044474704762506395,
      0.16283114271980018,
      78.27723661857458
     ],
     "n_zero": 6,
     "n_negative": 0,
     "FD_crosscheck_rel": 1.744207199115686e-11
    },
    "ladder_rel_diff_sm_vs_sp": 0.19975982960358235
   }
  ]
 },
 "SP4": {
  "ok": false,
  "sp": {
   "hedgehog": {
    "E": 13.775682566623857,
    "core": {
     "core_lams": [
      0.5427454085258073,
      0.4160402542747282,
      0.36166880663430573
     ],
     "core_spread": 0.1810766018915016,
     "core_spread_over_vacuum_aniso": 0.1810766018915016,
     "core_mean": 0.4401514898116137,
     "a_predicted": 0.43333333333333335,
     "n_cells": 2
    },
    "q_meridional": 0.9930820281085847,
    "r_half": 4.5
   },
   "fire_tail": {
    "it": 4000,
    "E": 13.775682566623857,
    "fmax": 0.026790398750786287,
    "dt": 0.0067571790191920675
   },
   "block_diag_max_offblock": 0.0,
   "loop": {
    "E": 18.340298906448407,
    "q_ring": 0.5,
    "fire_tail": {
     "it": 1200,
     "E": 18.340298906448407,
     "fmax": 0.010080315282012128,
     "dt": 0.019525285804444376
    }
   }
  },
  "sm": {
   "hedgehog": {
    "E": 13.925768199967072,
    "core": {
     "core_lams": [
      0.5446552531228372,
      0.41730263209260343,
      0.3622532650651862
     ],
     "core_spread": 0.18240198805765107,
     "core_spread_over_vacuum_aniso": 0.18240198805765107,
     "core_mean": 0.44140371676020895,
     "a_predicted": 0.43333333333333335,
     "n_cells": 2
    },
    "q_meridional": 0.9931934676348845,
    "r_half": 4.5
   },
   "fire_tail": {
    "it": 4000,
    "E": 13.925768199967072,
    "fmax": 0.025773942657744298,
    "dt": 0.0067571790191920675
   },
   "block_diag_max_offblock": 0.0,
   "loop": {
    "E": 18.848635119916917,
    "q_ring": 0.5,
    "fire_tail": {
     "it": 1200,
     "E": 18.848635119916917,
     "fmax": 0.009852228429465981,
     "dt": 0.019525285804444376
    }
   }
  },
  "compare": {
   "E_rel_diff": 0.010894968914777918,
   "q_abs_diff": 0.0001114395262997725,
   "core_lams_abs_diff": 0.0019098445970299194,
   "r_half_equal": true,
   "loop_E_rel_diff": 0.027716899057178425,
   "loop_q_abs_diff": 0.0
  }
 },
 "SP5": {
  "vacuum": {
   "rows": [
    {
     "eps": 0.02,
     "sp": {
      "dE_plus": 0.03465973180994287,
      "dE_minus": 0.03465973180994287,
      "odd_part": 0.0
     },
     "sm": {
      "dE_plus": 0.020843178973332398,
      "dE_minus": 0.020843178973332398,
      "odd_part": 0.0
     },
     "cross_sign_diff": 0.013816552836610471
    },
    {
     "eps": 0.05,
     "sp": {
      "dE_plus": 1.3780401800710855,
      "dE_minus": 1.3780401800710855,
      "odd_part": 0.0
     },
     "sm": {
      "dE_plus": 0.8383368472876369,
      "dE_minus": 0.8383368472876369,
      "odd_part": 0.0
     },
     "cross_sign_diff": 0.5397033327834486
    },
    {
     "eps": 0.1,
     "sp": {
      "dE_plus": 22.102387897619277,
      "dE_minus": 22.102387897619277,
      "odd_part": 0.0
     },
     "sm": {
      "dE_plus": 13.467463852887054,
      "dE_minus": 13.467463852887054,
      "odd_part": 0.0
     },
     "cross_sign_diff": 8.634924044732223
    },
    {
     "eps": 0.2,
     "sp": {
      "dE_plus": 353.76305823416845,
      "dE_minus": 353.76305823416845,
      "odd_part": 0.0
     },
     "sm": {
      "dE_plus": 215.62534742650877,
      "dE_minus": 215.62534742650877,
      "odd_part": 0.0
     },
     "cross_sign_diff": 138.1377108076597
    }
   ],
   "cross_diff_leading_power": 3.999918336399696
  },
  "hedgehog": {
   "rows": [
    {
     "eps": 0.02,
     "sp": {
      "dE_plus": -0.0036335521407462323,
      "dE_minus": -0.0036335521407462323,
      "odd_part": 0.0
     },
     "sm": {
      "dE_plus": -0.0041060936800541015,
      "dE_minus": -0.0041060936800541015,
      "odd_part": 0.0
     },
     "cross_sign_diff": 0.00047254153930786913
    },
    {
     "eps": 0.05,
     "sp": {
      "dE_plus": 0.033191314359514834,
      "dE_minus": 0.033191314359514834,
      "odd_part": 0.0
     },
     "sm": {
      "dE_plus": 0.015471312464843123,
      "dE_minus": 0.015471312464843123,
      "odd_part": 0.0
     },
     "cross_sign_diff": 0.01772000189467171
    },
    {
     "eps": 0.1,
     "sp": {
      "dE_plus": 0.9312815541486721,
      "dE_minus": 0.9312815541486721,
      "odd_part": 0.0
     },
     "sm": {
      "dE_plus": 0.6494599889881378,
      "dE_minus": 0.6494599889881378,
      "odd_part": 0.0
     },
     "cross_sign_diff": 0.28182156516053425
    },
    {
     "eps": 0.2,
     "sp": {
      "dE_plus": 16.49703522098037,
      "dE_minus": 16.49703522098037,
      "odd_part": 0.0
     },
     "sm": {
      "dE_plus": 11.995316398814206,
      "dE_minus": 11.995316398814206,
      "odd_part": 0.0
     },
     "cross_sign_diff": 4.501718822166163
    }
   ],
   "cross_diff_leading_power": 3.97930102352834
  }
 }
}